src/ConsoleLogger.py
src/TimeLimitGenerator.py
src/__init__.py
src/CallOnce/CallOnce.py
src/CallOnce/Enums.py
src/CallOnce/ResultContainer.py
src/CallOnce/__init__.py
src/Constraints/BaseChecker.py
src/Constraints/Constraints.py
src/Constraints/Exceptions.py
src/Constraints/VersionChecker.py
src/Constraints/__init__.py
src/InlineClass/InlineClass.py
src/InlineClass/__init__.py
src/RRExceptions/Exceptions.py
src/RRExceptions/__init__.py
src/StopWatch/StopWatch.py
src/StopWatch/__init__.py
src/Version/Version.py
src/Version/VersionException.py
src/Version/__init__.py
tests/__init__.py
tests/test_InlineClass.py
tests/test_StopWatch.py
tests/test_Version.py
tests/CallOnce/TestsArgumentsHash.py
tests/CallOnce/TestsFreeFunction.py
tests/CallOnce/TestsInClassMethod.py
tests/CallOnce/TestsInSelfMethod.py
tests/CallOnce/TestsNestedFunction.py
tests/CallOnce/TestsTtl.py
tests/CallOnce/__init__.py
rr_utils-1.1.2.dist-info/LICENSE
rr_utils-1.1.2.dist-info/METADATA
rr_utils-1.1.2.dist-info/WHEEL
rr_utils-1.1.2.dist-info/top_level.txt
rr_utils-1.1.2.dist-info/RECORD
