Metadata-Version: 2.1
Name: rr-utils
Version: 1.1.2
Summary: It is a set of useful classes for python. 
Home-page: https://github.com/RobertOlechowski/RR_Utils_Python
Author: Robert Olechowski
Author-email: RobertOlechowski@gmail.com
License: MIT
Platform: UNKNOWN
Classifier: Programming Language :: Python :: 3
Classifier: License :: OSI Approved :: MIT License
Classifier: Operating System :: OS Independent
Requires-Python: >=3.6
